README.md
setup.py
datasnake/__init__.py
datasnake/__main__.py
datasnake.egg-info/PKG-INFO
datasnake.egg-info/SOURCES.txt
datasnake.egg-info/dependency_links.txt
datasnake.egg-info/entry_points.txt
datasnake.egg-info/requires.txt
datasnake.egg-info/top_level.txt