Metadata-Version: 1.0
Name: datasnake
Version: 0.1.5
Summary: CLI for fast and easy database queries, tailing, pagination, introspection. DB engine agnostic. Backbone of Splunk TA-DataSnake.
Home-page: https://github.com/sodle/datasnake-core
Author: Scott Odle (Arizona State University)
Author-email: scott.odle@asu.edu
License: ['GPL v3']
Platform: UNKNOWN
